odoo/addons/l10n_it_fatturapa_pec/README.rst
odoo/addons/l10n_it_fatturapa_pec/__init__.py
odoo/addons/l10n_it_fatturapa_pec/__manifest__.py
odoo/addons/l10n_it_fatturapa_pec/data/config_parameter.xml
odoo/addons/l10n_it_fatturapa_pec/data/fetchmail_data.xml
odoo/addons/l10n_it_fatturapa_pec/data/sdi_channel_demo.xml
odoo/addons/l10n_it_fatturapa_pec/i18n/it.po
odoo/addons/l10n_it_fatturapa_pec/i18n/l10n_it_fatturapa_pec.pot
odoo/addons/l10n_it_fatturapa_pec/migrations/14.0.1.0.4/pre-migration.py
odoo/addons/l10n_it_fatturapa_pec/models/__init__.py
odoo/addons/l10n_it_fatturapa_pec/models/company.py
odoo/addons/l10n_it_fatturapa_pec/models/fatturapa_attachment_out.py
odoo/addons/l10n_it_fatturapa_pec/models/fetchmail.py
odoo/addons/l10n_it_fatturapa_pec/models/ir_mail_server.py
odoo/addons/l10n_it_fatturapa_pec/models/mail_thread.py
odoo/addons/l10n_it_fatturapa_pec/models/sdi.py
odoo/addons/l10n_it_fatturapa_pec/readme/CONFIGURE.rst
odoo/addons/l10n_it_fatturapa_pec/readme/CONTRIBUTORS.rst
odoo/addons/l10n_it_fatturapa_pec/readme/DESCRIPTION.rst
odoo/addons/l10n_it_fatturapa_pec/readme/USAGE.rst
odoo/addons/l10n_it_fatturapa_pec/security/ir.model.access.csv
odoo/addons/l10n_it_fatturapa_pec/static/description/icon.png
odoo/addons/l10n_it_fatturapa_pec/static/description/index.html
odoo/addons/l10n_it_fatturapa_pec/tests/__init__.py
odoo/addons/l10n_it_fatturapa_pec/tests/e_invoice_common.py
odoo/addons/l10n_it_fatturapa_pec/tests/test_e_invoice_response.py
odoo/addons/l10n_it_fatturapa_pec/tests/test_e_invoice_send.py
odoo/addons/l10n_it_fatturapa_pec/tests/data/ACCETTAZIONE_ IT03339130126_00009.xml.txt
odoo/addons/l10n_it_fatturapa_pec/tests/data/CONSEGNA_ IT03339130126_00009.xml.txt
odoo/addons/l10n_it_fatturapa_pec/tests/data/POSTA CERTIFICATA_ Invio File 7339338 (base64).txt
odoo/addons/l10n_it_fatturapa_pec/tests/data/POSTA CERTIFICATA_ Invio File 7339338 (broken XML).txt
odoo/addons/l10n_it_fatturapa_pec/tests/data/POSTA CERTIFICATA_ Invio File 7339338.txt
odoo14_addon_l10n_it_fatturapa_pec-14.0.2.6.1.dist-info/METADATA
odoo14_addon_l10n_it_fatturapa_pec-14.0.2.6.1.dist-info/WHEEL
odoo14_addon_l10n_it_fatturapa_pec-14.0.2.6.1.dist-info/top_level.txt
odoo14_addon_l10n_it_fatturapa_pec-14.0.2.6.1.dist-info/RECORD
