Metadata-Version: 2.1
Name: odoo14-addon-l10n_it_fatturapa_pec
Version: 14.0.2.6.1
Summary: Invio fatture elettroniche tramite PEC
Home-page: https://github.com/OCA/l10n-italy
Author: Openforce Srls Unipersonale, Odoo Community Association (OCA)
Author-email: support@odoo-community.org
License: AGPL-3
Classifier: Programming Language :: Python
Classifier: Framework :: Odoo
Classifier: Framework :: Odoo :: 14.0
Classifier: License :: OSI Approved :: GNU Affero General Public License v3
Requires-Python: >=3.6
Requires-Dist: odoo14-addon-l10n-it-fatturapa-in
Requires-Dist: odoo14-addon-l10n-it-fatturapa-out
Requires-Dist: odoo14-addon-l10n-it-sdi-channel
Requires-Dist: odoo<14.1dev,>=14.0a
